mpol/__init__.py
mpol/constants.py
mpol/coordinates.py
mpol/crossval.py
mpol/datasets.py
mpol/exceptions.py
mpol/fourier.py
mpol/geometry.py
mpol/gridding.py
mpol/images.py
mpol/losses.py
mpol/onedim.py
mpol/plot.py
mpol/precomposed.py
mpol/protocols.py
mpol/spheroidal_gridding.py
mpol/training.py
mpol/utils.py
MPoL-0.2.0.dist-info/LICENSE
MPoL-0.2.0.dist-info/METADATA
MPoL-0.2.0.dist-info/WHEEL
MPoL-0.2.0.dist-info/top_level.txt
MPoL-0.2.0.dist-info/RECORD
