Metadata-Version: 2.1
Name: MPoL
Version: 0.2.0
Summary: Regularized Maximum Likelihood Imaging for Radio Astronomy
Home-page: https://github.com/iancze/MPoL
Author: Ian Czekala
Author-email: iancze@gmail.com
Classifier: Programming Language :: Python :: 3.8
Classifier: Programming Language :: Python :: 3.9
Classifier: Programming Language :: Python :: 3.10
Classifier: License :: OSI Approved :: MIT License
Classifier: Operating System :: OS Independent
Requires-Python: >=3.8
License-File: LICENSE
Requires-Dist: numpy
Requires-Dist: fast-histogram
Requires-Dist: scipy
Requires-Dist: torch >=1.8.0
Requires-Dist: torchvision
Requires-Dist: torchaudio
Requires-Dist: torchkbnufft
Requires-Dist: astropy
Provides-Extra: analysis
Requires-Dist: frank >=1.2.1 ; extra == 'analysis'
Provides-Extra: dev
Requires-Dist: pytest ; extra == 'dev'
Requires-Dist: pytest-cov ; extra == 'dev'
Requires-Dist: matplotlib ; extra == 'dev'
Requires-Dist: requests ; extra == 'dev'
Requires-Dist: astropy ; extra == 'dev'
Requires-Dist: tensorboard ; extra == 'dev'
Requires-Dist: mypy ; extra == 'dev'
Requires-Dist: frank >=1.2.1 ; extra == 'dev'
Requires-Dist: sphinx >=5.3.0 ; extra == 'dev'
Requires-Dist: numpy ; extra == 'dev'
Requires-Dist: jupytext ; extra == 'dev'
Requires-Dist: ipython !=8.7.0 ; extra == 'dev'
Requires-Dist: nbsphinx ; extra == 'dev'
Requires-Dist: sphinx-book-theme >=0.9.3 ; extra == 'dev'
Requires-Dist: sphinx-copybutton ; extra == 'dev'
Requires-Dist: jupyter ; extra == 'dev'
Requires-Dist: nbconvert ; extra == 'dev'
Requires-Dist: sphinxcontrib-mermaid >=0.8.1 ; extra == 'dev'
Requires-Dist: myst-nb ; extra == 'dev'
Requires-Dist: jupyter-cache ; extra == 'dev'
Requires-Dist: Pillow ; extra == 'dev'
Requires-Dist: asdf ; extra == 'dev'
Requires-Dist: pyro-ppl ; extra == 'dev'
Requires-Dist: arviz[all] ; extra == 'dev'
Requires-Dist: pylint ; extra == 'dev'
Requires-Dist: black ; extra == 'dev'
Requires-Dist: pre-commit ; extra == 'dev'
Provides-Extra: docs
Requires-Dist: sphinx >=5.3.0 ; extra == 'docs'
Requires-Dist: numpy ; extra == 'docs'
Requires-Dist: jupytext ; extra == 'docs'
Requires-Dist: ipython !=8.7.0 ; extra == 'docs'
Requires-Dist: nbsphinx ; extra == 'docs'
Requires-Dist: sphinx-book-theme >=0.9.3 ; extra == 'docs'
Requires-Dist: sphinx-copybutton ; extra == 'docs'
Requires-Dist: jupyter ; extra == 'docs'
Requires-Dist: nbconvert ; extra == 'docs'
Requires-Dist: matplotlib ; extra == 'docs'
Requires-Dist: sphinxcontrib-mermaid >=0.8.1 ; extra == 'docs'
Requires-Dist: astropy ; extra == 'docs'
Requires-Dist: tensorboard ; extra == 'docs'
Requires-Dist: myst-nb ; extra == 'docs'
Requires-Dist: jupyter-cache ; extra == 'docs'
Requires-Dist: Pillow ; extra == 'docs'
Requires-Dist: asdf ; extra == 'docs'
Requires-Dist: pyro-ppl ; extra == 'docs'
Requires-Dist: arviz[all] ; extra == 'docs'
Provides-Extra: test
Requires-Dist: pytest ; extra == 'test'
Requires-Dist: pytest-cov ; extra == 'test'
Requires-Dist: matplotlib ; extra == 'test'
Requires-Dist: requests ; extra == 'test'
Requires-Dist: astropy ; extra == 'test'
Requires-Dist: tensorboard ; extra == 'test'
Requires-Dist: mypy ; extra == 'test'
Requires-Dist: frank >=1.2.1 ; extra == 'test'
